CHANGES.txt
README.txt
bootstrap.py
buildout.cfg
setup.py
src/chameleon/__init__.py
src/chameleon.html.egg-info/PKG-INFO
src/chameleon.html.egg-info/SOURCES.txt
src/chameleon.html.egg-info/dependency_links.txt
src/chameleon.html.egg-info/namespace_packages.txt
src/chameleon.html.egg-info/not-zip-safe
src/chameleon.html.egg-info/requires.txt
src/chameleon.html.egg-info/top_level.txt
src/chameleon/html/__init__.py
src/chameleon/html/interfaces.py
src/chameleon/html/language.py
src/chameleon/html/language.txt
src/chameleon/html/template.py
src/chameleon/html/template.txt
src/chameleon/html/xss.py
src/chameleon/html/tests/__init__.py
src/chameleon/html/tests/test_doctests.py
src/chameleon/html/tests/layouts/example.html
src/chameleon/html/tests/layouts/example.xss