Metadata-Version: 1.0
Name: chameleon.html
Version: 0.1
Summary: Dynamic HTML template compiler with XSS language support.
Home-page: UNKNOWN
Author: Malthe Borch and the Zope Community
Author-email: zope-dev@zope.org
License: BSD
Platform: UNKNOWN
Classifier: Programming Language :: Python
Classifier: Topic :: Text Processing :: Markup :: HTML
Classifier: Topic :: Text Processing :: Markup :: XML
Classifier: Topic :: Software Development :: Libraries :: Python Modules
